py_debug/__init__.py
py_debugs-1.0.2.dist-info/licenses/LICENSE
py_debugs-1.0.2.dist-info/METADATA
py_debugs-1.0.2.dist-info/WHEEL
py_debugs-1.0.2.dist-info/top_level.txt
py_debugs-1.0.2.dist-info/RECORD
