Metadata-Version: 2.4
Name: py-debugs
Version: 1.0.2
Summary: This is the simplest module for logging functions.
Author-email: DDSurok <ddsurok@gmail.com>
License: MIT
Project-URL: Homepage, https://github.io/DDSurok/py-debug
Requires-Python: >=3.8
License-File: LICENSE
Dynamic: license-file
